{"nm":"newScene","ddd":0,"h":55,"w":112,"meta":{"g":"SVG to Lottie v0.15.1-0.6.0"},"layers":[{"ty":4,"nm":"","sr":1,"st":0,"op":115,"ip":0,"hd":false,"ddd":0,"bm":0,"hasMask":false,"ao":0,"ks":{"a":{"a":0,"k":[0,0]},"s":{"a":0,"k":[100,100]},"sk":{"a":0,"k":0},"p":{"a":0,"k":[0,0]},"r":{"a":0,"k":0},"sa":{"a":0,"k":0},"o":{"a":0,"k":100}},"ef":[],"shapes":[{"ty":"gr","bm":0,"hd":false,"nm":"","it":[{"ty":"sh","bm":0,"hd":false,"nm":"","d":1,"ks":{"a":0,"k":{"c":false,"i":[[0,0],[0,0],[0,0],[0,0],[0,0],[0,0],[0,0]],"o":[[0,0],[0,0],[0,0],[0,0],[0,0],[0,0],[0,0]],"v":[[8,27.5],[42.3521,27.5],[45.0872,21.9286],[56.0273,47],[66.9675,8],[75.1726,27.5],[104,27.5]]}}},{"ty":"st","bm":0,"hd":false,"nm":"","lc":2,"lj":2,"ml":4,"o":{"a":0,"k":100},"w":{"a":0,"k":3},"c":{"a":0,"k":[0.9725,0.9765,0.9804]}},{"ty":"tm","bm":0,"hd":false,"nm":"","e":{"a":1,"k":[{"o":{"x":0.167,"y":0.167},"i":{"x":0.833,"y":0.833},"s":[0],"t":0},{"s":[100],"t":90}]},"o":{"a":0,"k":0},"s":{"a":null,"k":0},"m":1},{"ty":"tr","a":{"a":0,"k":[0,0]},"s":{"a":0,"k":[100,100]},"sk":{"a":0,"k":0},"p":{"a":0,"k":[0,0]},"r":{"a":0,"k":0},"sa":{"a":0,"k":0},"o":{"a":0,"k":100}}]}],"ind":1}],"v":"5.7.0","fr":60,"op":115,"ip":0,"assets":[]}